batch_pipeline_classes/AWSProcessor.py
batch_pipeline_classes/BaseProcessor.py
batch_pipeline_classes/GCPProcessor.py
batch_pipeline_classes/__init__.py
batch_pipeline_classes-0.0.16.dist-info/METADATA
batch_pipeline_classes-0.0.16.dist-info/WHEEL
batch_pipeline_classes-0.0.16.dist-info/top_level.txt
batch_pipeline_classes-0.0.16.dist-info/RECORD
