Metadata-Version: 2.4
Name: batch-pipeline-classes
Version: 0.0.16
Requires-Dist: google-cloud-bigquery
Requires-Dist: boto3
Dynamic: requires-dist
